stackpeanut/__init__.py
stackpeanut/stackpeanut.py
stackpeanut/stackpotato.py
stackpeanut-0.0.3.dist-info/LICENSE.txt
stackpeanut-0.0.3.dist-info/METADATA
stackpeanut-0.0.3.dist-info/WHEEL
stackpeanut-0.0.3.dist-info/top_level.txt
stackpeanut-0.0.3.dist-info/RECORD
