Metadata-Version: 2.1
Name: stackpeanut
Version: 0.0.3
Summary: a package that contain my lovely peanut
Home-page: UNKNOWN
Author: Isara_stackpython
Author-email: author@example.com
License: UNKNOWN
Platform: UNKNOWN
Classifier: Programming Language :: Python :: 3
Classifier: License :: OSI Approved :: MIT License
Classifier: Operating System :: OS Independent
Requires-Python: >=3.6
Requires-Dist: numpy
